<Properties StartupConfiguration="{82776875-2617-72E5-61A9-91C614F25CB3}|">
  <MonoDevelop.Ide.Workbench ActiveDocument="Assets/Scripts/BattleSystem.cs">
    <Files>
      <File FileName="Assets/Scripts/Card.cs" Line="19" Column="1" IsPinned="True" />
      <File FileName="Assets/Scripts/DragDrop.cs" Line="14" Column="25" />
      <File FileName="Assets/Scripts/Player.cs" Line="14" Column="6" />
      <File FileName="Assets/Scripts/healthbar.cs" Line="4" Column="22" />
      <File FileName="Assets/Scripts/BattleSystem.cs" Line="28" Column="40" />
    </Files>
    <Pads>
      <Pad Id="ProjectPad">
        <State name="__root__">
          <Node name="Hamlet Media Project" expanded="True" selected="True" />
        </State>
      </Pad>
    </Pads>
  </MonoDevelop.Ide.Workbench>
  <MonoDevelop.Ide.DebuggingService.PinnedWatches />
  <MonoDevelop.Ide.Workspace ActiveConfiguration="Debug" />
  <MonoDevelop.Ide.ItemProperties.Assembly-CSharp PreferredExecutionTarget="7652886b-5ed0-43e7-b8ad-6073d2baef33" />
  <MonoDevelop.Ide.DebuggingService.Breakpoints>
    <BreakpointStore />
  </MonoDevelop.Ide.DebuggingService.Breakpoints>
  <MultiItemStartupConfigurations />
</Properties>